biomap/__init__.py
biomap/mappers/__init__.py
biomap/mappers/hgnc/__init__.py
biomap/mappers/hgnc/hgnc.py
biomap_hgnc-0.0.54.dist-info/LICENSE
biomap_hgnc-0.0.54.dist-info/METADATA
biomap_hgnc-0.0.54.dist-info/WHEEL
biomap_hgnc-0.0.54.dist-info/top_level.txt
biomap_hgnc-0.0.54.dist-info/RECORD
